{
  "hash": "c2c161fc",
  "browserHash": "a55a5878",
  "optimized": {
    "@vue/devtools-api": {
      "src": "../../../node_modules/@vue/devtools-api/lib/esm/index.js",
      "file": "@vue_devtools-api.js",
      "fileHash": "a235f902",
      "needsInterop": false
    },
    "@vueuse/core": {
      "src": "../../../node_modules/@vueuse/core/index.mjs",
      "file": "@vueuse_core.js",
      "fileHash": "9fe86a45",
      "needsInterop": false
    },
    "vue": {
      "src": "../../../node_modules/@vue/runtime-dom/dist/runtime-dom.esm-bundler.js",
      "file": "vue.js",
      "fileHash": "6e5902db",
      "needsInterop": false
    },
    "vue-router": {
      "src": "../../../node_modules/vue-router/dist/vue-router.esm-bundler.js",
      "file": "vue-router.js",
      "fileHash": "2ca2005e",
      "needsInterop": false
    },
    "nprogress": {
      "src": "../../../node_modules/nprogress/nprogress.js",
      "file": "nprogress.js",
      "fileHash": "8c53231e",
      "needsInterop": true
    },
    "@vuepress/shared": {
      "src": "../../../node_modules/@vuepress/shared/lib/esm/index.js",
      "file": "@vuepress_shared.js",
      "fileHash": "74817b49",
      "needsInterop": false
    }
  },
  "chunks": {
    "chunk-ORQJXVYI": {
      "file": "chunk-ORQJXVYI.js"
    },
    "chunk-VRCAGUXH": {
      "file": "chunk-VRCAGUXH.js"
    },
    "chunk-YLVLMH7X": {
      "file": "chunk-YLVLMH7X.js"
    },
    "chunk-2Z6DPKHT": {
      "file": "chunk-2Z6DPKHT.js"
    }
  }
}